{
	"slideList":[
		{
			"url":"/resources/images/about/banner/banner_01.png",
			"href":"/resources/html/downloadApp.html",
			"title":"",
			"desc":""
		}
	],
	"intro":{
		"title":"产品介绍",
		"list":[
			{
				"icon":"/resources/images/about/phone.png",
				"desc":"“求苗”是由深圳华体星空体育文化有限公司研发并发行的体育消费服务综合平台。目前，产品配备移动端（IOS、安卓、H5）的求苗应用，配以PC专业化、标准化的管理后台。"
			},
			{
				"icon":"/resources/images/about/computer.png",
				"desc":"“求苗”是一个为体育产业机构（B端）和体育爱好者（C端），提供体育产品资源互通及健康运动服务的互联网平台。"
			},
			{
				"icon":"/resources/images/about/more.png",
				"desc":"“求苗”能让体育爱好人士、球队、俱乐部、赛事、赞助商、媒体机构和其他组织在求苗平台通过线上形式，完成组建球队、发布活动、寻找赞助、增加曝光、获取收益、数据统计的消费和服务。"
			}
		]
	},
	"advantage":{
		"title":"亮点及优势",
		"desc":[
			"打造体育IP服务平台，面向各类体育IP共享体育产业的专业服务。",
			"为体育产业提供专业化的工作环境和盈利模式，为消费端用户提供专属运动社区。"
		]
	},
	"service":{
		"title":"服务内容",
		"list":[
			{
				"icon":"/resources/images/about/community.png",
				"title":"体育圈社区"
			},
			{
				"icon":"/resources/images/about/news.png",
				"title":"资讯发布和推送"
			},
			{
				"icon":"/resources/images/about/intro_02.png",
				"title":" 体育视频和赛事直播"
			},
			{
				"icon":"/resources/images/about/city_01.png",
				"title":"同城服务"
			},
			{
				"icon":"/resources/images/about/data_base.png",
				"title":"体育数据库"
			},
			{
				"icon":"/resources/images/about/backstage_01.png",
				"title":"后台数据统计"
			},
			{
				"icon":"/resources/images/about/operate_01.png",
				"title":"赛事的发布、监控和媒体运作"
			},
			{
				"icon":"/resources/images/about/shop_01.png",
				"title":"运动周边商城"
			}
		]
	}
}